myrai/__init__.py
myrai/_util.py
myrai/mirai.py
myrai/mirai_types.py
myrai/mirai_types.pyi
myrai/py.typed
myrai/jvm/__init__.py
myrai/jvm/java.py
myrai/resources/myrai-0.1.0.jar
myrai-0.1.0.dist-info/LICENSE
myrai-0.1.0.dist-info/METADATA
myrai-0.1.0.dist-info/WHEEL
myrai-0.1.0.dist-info/top_level.txt
myrai-0.1.0.dist-info/RECORD
